squirrel/__init__.py
squirrel/artifact_manager/__init__.py
squirrel/artifact_manager/base.py
squirrel/artifact_manager/drivers.py
squirrel/artifact_manager/filesystem.py
squirrel/artifact_manager/wandb.py
squirrel/benchmark/msgpack_caching.py
squirrel/benchmark/quantify_randomness.py
squirrel/catalog/__init__.py
squirrel/catalog/catalog.py
squirrel/catalog/source.py
squirrel/catalog/yaml.py
squirrel/constants.py
squirrel/driver/__init__.py
squirrel/driver/csv.py
squirrel/driver/data_frame.py
squirrel/driver/driver.py
squirrel/driver/excel.py
squirrel/driver/feather.py
squirrel/driver/file.py
squirrel/driver/jsonl.py
squirrel/driver/msgpack.py
squirrel/driver/parquet.py
squirrel/driver/source_combiner.py
squirrel/driver/store.py
squirrel/driver/zarr.py
squirrel/framework/__init__.py
squirrel/framework/exceptions.py
squirrel/framework/io.py
squirrel/framework/plugins/__init__.py
squirrel/framework/plugins/hookimpl.py
squirrel/framework/plugins/hookspec.py
squirrel/framework/plugins/plugin_manager.py
squirrel/fsspec/__init__.py
squirrel/fsspec/custom_gcsfs.py
squirrel/fsspec/fs.py
squirrel/integration_test/__init__.py
squirrel/integration_test/conftest.py
squirrel/integration_test/helpers.py
squirrel/integration_test/shared_fixtures.py
squirrel/integration_test/test_jsonl/test_torch_distibuted_loading.py
squirrel/iterstream/__init__.py
squirrel/iterstream/base.py
squirrel/iterstream/iterators.py
squirrel/iterstream/metrics.py
squirrel/iterstream/multiplexer.py
squirrel/iterstream/source.py
squirrel/iterstream/torch_composables.py
squirrel/py.typed
squirrel/serialization/__init__.py
squirrel/serialization/jsonl.py
squirrel/serialization/msgpack.py
squirrel/serialization/serializer.py
squirrel/store/__init__.py
squirrel/store/filesystem.py
squirrel/store/squirrel_store.py
squirrel/store/store.py
squirrel/zarr/__init__.py
squirrel/zarr/group.py
squirrel/zarr/key.py
squirrel/zarr/store.py
squirrel/zarr/sync.py
squirrel_core-0.20.2.dist-info/LICENSE
squirrel_core-0.20.2.dist-info/METADATA
squirrel_core-0.20.2.dist-info/WHEEL
squirrel_core-0.20.2.dist-info/entry_points.txt
squirrel_core-0.20.2.dist-info/RECORD
