Metadata-Version: 2.1
Name: squirrel-core
Version: 0.20.2
Summary: Squirrel is a Python library that enables ML teams to share, load, and transform data in a collaborative, flexible and efficient way.
Home-page: https://merantix-momentum.com/technology/squirrel/
License: Apache 2.0
Author: Merantix Momentum
Requires-Python: >=3.9,<4.0
Classifier: Development Status :: 5 - Production/Stable
Classifier: License :: OSI Approved :: Apache Software License
Classifier: License :: Other/Proprietary License
Classifier: Programming Language :: Python :: 3
Classifier: Programming Language :: Python :: 3.9
Classifier: Programming Language :: Python :: 3.10
Classifier: Programming Language :: Python :: 3.11
Classifier: Programming Language :: Python :: 3.12
Classifier: Typing :: Typed
Provides-Extra: all
Provides-Extra: azure
Provides-Extra: dask
Provides-Extra: excel
Provides-Extra: feather
Provides-Extra: gcp
Provides-Extra: numba
Provides-Extra: parquet
Provides-Extra: s3
Provides-Extra: torch
Provides-Extra: wandb
Provides-Extra: zarr
Requires-Dist: adlfs (<2021.10) ; extra == "azure" or extra == "all"
Requires-Dist: aiohttp (>=3.8.4)
Requires-Dist: dask[dataframe,distributed] (>=2023.2.0) ; extra == "dask" or extra == "all"
Requires-Dist: fsspec (>=2021.7.0)
Requires-Dist: gcsfs (>=2021.7.0) ; extra == "gcp" or extra == "all"
Requires-Dist: mako (>=1.2.4)
Requires-Dist: more-itertools (>=9.0.0)
Requires-Dist: msgpack (>=1.0.4)
Requires-Dist: msgpack-numpy (>=0.4.8)
Requires-Dist: numba (>=0.56.4) ; extra == "numba" or extra == "all"
Requires-Dist: numpy (>=1.23.5)
Requires-Dist: oauthlib (>=3.2.2)
Requires-Dist: odfpy (>=1.4.1) ; extra == "excel" or extra == "all"
Requires-Dist: openpyxl (>=3.1.1) ; extra == "excel" or extra == "all"
Requires-Dist: pandas (>=2.0.3,<3.0.0)
Requires-Dist: pluggy (>=1.0.0)
Requires-Dist: pyarrow (>=14.0.1) ; extra == "feather" or extra == "parquet" or extra == "all"
Requires-Dist: pyjwt (>=2.6.0)
Requires-Dist: pyxlsb (>=1.0.10) ; extra == "excel" or extra == "all"
Requires-Dist: ruamel-yaml (>=0.17.21)
Requires-Dist: s3fs (>=2021.7.0) ; extra == "s3" or extra == "all"
Requires-Dist: torch (>=1.13.1) ; extra == "torch" or extra == "all"
Requires-Dist: tqdm (>=4.64.1)
Requires-Dist: urllib3 (>=1.25.4,<1.27)
Requires-Dist: wandb ; extra == "wandb" or extra == "all"
Requires-Dist: xlrd (>=2.0.1) ; extra == "excel" or extra == "all"
Requires-Dist: zarr (>=2.10.3) ; extra == "zarr" or extra == "all"
Project-URL: Documentation, https://squirrel-core.readthedocs.io/en/latest/
Project-URL: Repository, https://github.com/merantix-momentum/squirrel-core
